{
    "雾岛圣": {
        "game_name": "AIR",
        "birthday": "1-3",
        "aliases": "",
        "img_path": [
            "雾岛圣.jpg"
        ],
        "cv": "冬马由美",
        "staff": "樋上いたる",
        "tag": null,
        "company_name": "Key",
        "like": null,
        "age": "172cm 87/59/86",
        "presenter": null,
        "others": null
    },
    "桐生美也": {
        "game_name": "Heaven Burns Red",
        "birthday": "1-5",
        "aliases": "",
        "img_path": [
            "桐生美也.webp"
        ],
        "cv": null,
        "staff": null,
        "tag": "30G",
        "company_name": "Key",
        "like": "日本传统文化、弓道",
        "age": "156cm",
        "presenter": null,
        "others": null
    },
    "泽渡真琴": {
        "game_name": "Kanon",
        "birthday": "1-6",
        "aliases": "",
        "img_path": [
            "泽渡真琴.jpeg"
        ],
        "cv": "飯塚雅弓",
        "staff": "樋上いたる",
        "tag": null,
        "company_name": "Key",
        "like": null,
        "age": null,
        "presenter": null,
        "others": null
    },
    "白河结奈": {
        "game_name": "Heaven Burns Red",
        "birthday": "1-6",
        "aliases": "",
        "img_path": [
            "白河结奈.webp"
        ],
        "cv": "花守ゆみり",
        "staff": null,
        "tag": "30G",
        "company_name": "Key",
        "like": null,
        "age": "164cm",
        "presenter": null,
        "others": null
    },
    "月宫亚由": {
        "game_name": "Kanon",
        "birthday": "1-7",
        "aliases": "",
        "img_path": [
            "月宫亚由.jpeg"
        ],
        "cv": "堀江由衣",
        "staff": "樋上いたる",
        "tag": null,
        "company_name": "Key",
        "like": null,
        "age": null,
        "presenter": null,
        "others": null
    },
    "直枝架夜": {
        "game_name": "Kud Wafter",
        "birthday": "1-12",
        "aliases": "",
        "img_path": [
            "直枝架夜.jpeg"
        ],
        "cv": "若林直美",
        "staff": null,
        "tag": null,
        "company_name": "Key",
        "like": null,
        "age": null,
        "presenter": null,
        "others": null
    },
    "水濑莓": {
        "game_name": "Heaven Burns Red",
        "birthday": "1-15",
        "aliases": "",
        "img_path": [
            "水濑莓.webp"
        ],
        "cv": "爱美",
        "staff": null,
        "tag": "31B",
        "company_name": "Key",
        "like": "棒球、蔬菜棒",
        "age": "172cm",
        "presenter": null,
        "others": null
    },
    "直枝理树": {
        "game_name": "Little Busters!",
        "birthday": "1-17",
        "aliases": "",
        "img_path": [
            "直枝理树.jpeg"
        ],
        "cv": "民安ともえ",
        "staff": null,
        "tag": null,
        "company_name": "Key",
        "like": null,
        "age": null,
        "presenter": null,
        "others": null
    },
    "伊吹公子": {
        "game_name": "CLANNAD",
        "birthday": "1-18",
        "aliases": "",
        "img_path": [
            "伊吹公子.jpeg"
        ],
        "cv": "皆口裕子",
        "staff": null,
        "tag": null,
        "company_name": "Key",
        "like": null,
        "age": null,
        "presenter": null,
        "others": null
    },
    "露娜Q": {
        "game_name": "LUNARiA!",
        "birthday": "1-23",
        "aliases": "",
        "img_path": [
            "露娜Q.png"
        ],
        "cv": "田中美海",
        "staff": null,
        "tag": null,
        "company_name": "Key",
        "like": null,
        "age": null,
        "presenter": null,
        "others": null
    },
    "芙里提卡": {
        "game_name": "Heaven Burns Red",
        "birthday": "1-26",
        "aliases": "",
        "img_path": [
            "芙里提卡.webp"
        ],
        "cv": "小坂井祐莉絵",
        "staff": null,
        "tag": "31X",
        "company_name": "Key",
        "like": "数学",
        "age": "131cm",
        "presenter": null,
        "others": null
    },
    "川澄舞": {
        "game_name": "Kanon",
        "birthday": "1-29",
        "aliases": "",
        "img_path": [
            "川澄舞.jpeg"
        ],
        "cv": "田村ゆかり",
        "staff": "樋上いたる",
        "tag": null,
        "company_name": "Key",
        "like": null,
        "age": null,
        "presenter": null,
        "others": null
    },
    "美坂栞": {
        "game_name": "Kanon",
        "birthday": "2-1",
        "aliases": "",
        "img_path": [
            "美坂栞.jpeg"
        ],
        "cv": "小西寛子",
        "staff": "樋上いたる",
        "tag": null,
        "company_name": "Key",
        "like": null,
        "age": null,
        "presenter": null,
        "others": null
    },
    "野村美希": {
        "game_name": "Summer Pockets",
        "birthday": "2-2",
        "aliases": "",
        "img_path": [
            "野村美希.png"
        ],
        "cv": "一宮朔",
        "staff": "ふむゆん",
        "tag": null,
        "company_name": "VISUAL ARTS / Key",
        "like": null,
        "age": null,
        "presenter": null,
        "others": null
    },
    "佐月麻里": {
        "game_name": "Heaven Burns Red",
        "birthday": "2-7",
        "aliases": "",
        "img_path": [
            "佐月麻里.webp"
        ],
        "cv": "宫本侑芽",
        "staff": null,
        "tag": "31C",
        "company_name": "Key、VISUAL ARTS",
        "like": null,
        "age": "150cm",
        "presenter": null,
        "others": null
    },
    "三谷良一": {
        "game_name": "Summer Pockets",
        "birthday": "2-9",
        "aliases": "",
        "img_path": [
            "三谷良一.png"
        ],
        "cv": "熊谷健太朗",
        "staff": null,
        "tag": null,
        "company_name": "Key、VISUAL ARTS",
        "like": null,
        "age": "175cm/65kg",
        "presenter": null,
        "others": null
    },
    "东城司": {
        "game_name": "Heaven Burns Red",
        "birthday": "2-14",
        "aliases": "",
        "img_path": [
            "东城司.webp"
        ],
        "cv": "天海由梨奈",
        "staff": null,
        "tag": "31A",
        "company_name": "Key",
        "like": null,
        "age": "163cm",
        "presenter": null,
        "others": null
    },
    "春原阳平": {
        "game_name": "CLANNAD",
        "birthday": "2-17",
        "aliases": "",
        "img_path": [
            "春原阳平.PNG"
        ],
        "cv": "阪口大助",
        "staff": "樋上いたる",
        "tag": null,
        "company_name": "Key、VISUAL ARTS",
        "like": null,
        "age": null,
        "presenter": null,
        "others": null
    },
    "千里朱音": {
        "game_name": "Rewrite",
        "birthday": "2-17",
        "aliases": "",
        "img_path": [
            "千里朱音.png"
        ],
        "cv": "喜多村英梨",
        "staff": "樋上いたる",
        "tag": null,
        "company_name": "Key",
        "like": null,
        "age": null,
        "presenter": null,
        "others": null
    },
    "神崎阿黛尔海德": {
        "game_name": "Heaven Burns Red",
        "birthday": "2-22",
        "aliases": "",
        "img_path": [
            "神崎阿黛尔海德.webp"
        ],
        "cv": "稗田宁宁",
        "staff": null,
        "tag": "31C",
        "company_name": "Key、VISUAL ARTS",
        "like": null,
        "age": "160cm",
        "presenter": null,
        "others": null
    },
    "町村玲央奈": {
        "game_name": "LOOPERS",
        "birthday": "2-24",
        "aliases": "",
        "img_path": [
            "町村玲央奈.png"
        ],
        "cv": "井泽诗织",
        "staff": null,
        "tag": null,
        "company_name": "Key、VISUAL ARTS",
        "like": "调戏昼田",
        "age": "158cm",
        "presenter": null,
        "others": null
    },
    "玛丽亚": {
        "game_name": "Heaven Burns Red",
        "birthday": "2-26",
        "aliases": "",
        "img_path": [
            "玛丽亚.webp"
        ],
        "cv": "亚月优音",
        "staff": null,
        "tag": "31X",
        "company_name": "VISUAL ARTS / Key",
        "like": null,
        "age": "170cm",
        "presenter": null,
        "others": null
    },
    "命吹雪": {
        "game_name": "Heaven Burns Red",
        "birthday": "3-4",
        "aliases": "",
        "img_path": [
            "命吹雪.webp"
        ],
        "cv": "浅见春那",
        "staff": null,
        "tag": "31D",
        "company_name": "Key、VISUAL ARTS",
        "like": null,
        "age": "154cm",
        "presenter": null,
        "others": null
    },
    "西门贵明": {
        "game_name": "LOOPERS",
        "birthday": "3-5",
        "aliases": "",
        "img_path": [
            "西门贵明.webp"
        ],
        "cv": "木村良平",
        "staff": null,
        "tag": null,
        "company_name": "Key、VISUAL ARTS",
        "like": null,
        "age": "181cm",
        "presenter": null,
        "others": null
    },
    "井上晶": {
        "game_name": "Rewrite",
        "birthday": "3-6",
        "aliases": "",
        "img_path": [
            "井上晶.png"
        ],
        "cv": "渡边佳美",
        "staff": "樋上いたる",
        "tag": null,
        "company_name": "VISUAL ARTS / Key",
        "like": null,
        "age": null,
        "presenter": null,
        "others": null
    },
    "来谷唯湖": {
        "game_name": "Little Busters!",
        "birthday": "3-13",
        "aliases": "",
        "img_path": [
            "来谷唯湖.png"
        ],
        "cv": "田中涼子",
        "staff": "樋上いたる",
        "tag": null,
        "company_name": "VISUAL ARTS / Key",
        "like": null,
        "age": null,
        "presenter": null,
        "others": null
    },
    "柊木梢": {
        "game_name": "Heaven Burns Red",
        "birthday": "3-18",
        "aliases": "",
        "img_path": [
            "柊木梢.png"
        ],
        "cv": "小泽亚李",
        "staff": null,
        "tag": "31B",
        "company_name": "VISUAL ARTS / Key",
        "like": null,
        "age": null,
        "presenter": null,
        "others": null
    },
    "小笠原绯雨": {
        "game_name": "Heaven Burns Red",
        "birthday": "3-21",
        "aliases": "",
        "img_path": [
            "小笠原绯雨.webp"
        ],
        "cv": "岭内美海/樱井海亚/田中美海",
        "staff": null,
        "tag": "30G",
        "company_name": "VISUAL ARTS / Key",
        "like": null,
        "age": "138cm",
        "presenter": null,
        "others": null
    },
    "有月椎菜": {
        "game_name": "Kud Wafter",
        "birthday": "3-25",
        "aliases": "",
        "img_path": [
            "有月椎菜.jpeg"
        ],
        "cv": null,
        "staff": null,
        "tag": null,
        "company_name": "VISUAL ARTS / Key",
        "like": null,
        "age": null,
        "presenter": null,
        "others": null
    },
    "华村诗纪": {
        "game_name": "Heaven Burns Red",
        "birthday": "3-25",
        "aliases": "",
        "img_path": [
            "华村诗纪.png"
        ],
        "cv": "时泽香保里",
        "staff": null,
        "tag": "31F",
        "company_name": "VISUAL ARTS / Key",
        "like": null,
        "age": "172cm",
        "presenter": null,
        "others": null
    },
    "凤咲夜": {
        "game_name": "Rewrite",
        "birthday": "3-27",
        "aliases": "",
        "img_path": [],
        "cv": "小西克幸",
        "staff": "樋上いたる",
        "tag": null,
        "company_name": "Key",
        "like": null,
        "age": null,
        "presenter": null,
        "others": null
    },
    "阿酱前辈": {
        "game_name": "Little Busters! EX",
        "birthday": "4-1",
        "aliases": "",
        "img_path": [
            "阿酱前辈.jpeg"
        ],
        "cv": "平井理子",
        "staff": "樋上いたる",
        "tag": null,
        "company_name": "Key",
        "like": null,
        "age": null,
        "presenter": null,
        "others": null
    },
    "丰厚弥生": {
        "game_name": "Heaven Burns Red",
        "birthday": "4-1",
        "aliases": "",
        "img_path": [
            "丰厚弥生.png"
        ],
        "cv": "白花恋香",
        "staff": null,
        "tag": "31C",
        "company_name": "Key、VISUAL ARTS",
        "like": null,
        "age": "121cm",
        "presenter": null,
        "others": null
    },
    "藤川美亚": {
        "game_name": "LOOPERS",
        "birthday": "4-2",
        "aliases": "",
        "img_path": [
            "藤川美亚.png"
        ],
        "cv": "金子彩花",
        "staff": "null",
        "tag": null,
        "company_name": "Key",
        "like": null,
        "age": null,
        "presenter": null,
        "others": null
    },
    "相乐美佐枝": {
        "game_name": "CLANNAD",
        "birthday": "4-3",
        "aliases": "",
        "img_path": [
            "相乐美佐枝.jpeg"
        ],
        "cv": "ゆきのさつき",
        "staff": "樋上いたる",
        "tag": null,
        "company_name": "Key、VISUAL ARTS",
        "like": null,
        "age": null,
        "presenter": null,
        "others": null
    },
    "久岛鸥": {
        "game_name": "Summer Pockets",
        "birthday": "4-4",
        "aliases": "",
        "img_path": [
            "久岛鸥.jpeg"
        ],
        "cv": "嶺内ともみ",
        "staff": "Na-Ga",
        "tag": null,
        "company_name": "VISUAL ARTS / Key",
        "like": null,
        "age": null,
        "presenter": null,
        "others": null
    },
    "神北小毬": {
        "game_name": "Little Busters!",
        "birthday": "4-5",
        "aliases": "",
        "img_path": [
            "神北小毬.jpeg"
        ],
        "cv": "やなせなつみ",
        "staff": "樋上いたる",
        "tag": null,
        "company_name": "Key、VISUAL ARTS",
        "like": null,
        "age": null,
        "presenter": null,
        "others": null
    },
    "白虎": {
        "game_name": "Heaven Burns Red",
        "birthday": "4-8",
        "aliases": "",
        "img_path": [
            "白虎.png"
        ],
        "cv": null,
        "staff": null,
        "tag": "31B",
        "company_name": "Key、VISUAL ARTS",
        "like": null,
        "age": null,
        "presenter": null,
        "others": null
    },
    "柳美音": {
        "game_name": "Heaven Burns Red",
        "birthday": "4-13",
        "aliases": "",
        "img_path": [
            "柳美音.webp"
        ],
        "cv": null,
        "staff": null,
        "tag": "31F",
        "company_name": "VISUAL ARTS / Key",
        "like": null,
        "age": "170cm",
        "presenter": null,
        "others": null
    },
    "北川润": {
        "game_name": "Kanon",
        "birthday": "4-18",
        "aliases": "",
        "img_path": [],
        "cv": null,
        "staff": null,
        "tag": null,
        "company_name": "VISUAL ARTS / Key",
        "like": null,
        "age": null,
        "presenter": null,
        "others": null
    },
    "松岗绮罗路": {
        "game_name": "Heaven Burns Red",
        "birthday": "4-26",
        "aliases": "",
        "img_path": [
            "松岗绮罗路.webp"
        ],
        "cv": "小岛ゆい",
        "staff": null,
        "tag": "31F",
        "company_name": "VISUAL ARTS / Key",
        "like": null,
        "age": "150cm",
        "presenter": null,
        "others": null
    },
    "水织静久": {
        "game_name": "Summer Pockets",
        "birthday": "4-29",
        "aliases": "",
        "img_path": [
            "水织静久.png"
        ],
        "cv": "小山さほみ",
        "staff": "永山ゆうのん",
        "tag": null,
        "company_name": "VISUAL ARTS / Key",
        "like": null,
        "age": null,
        "presenter": null,
        "others": null
    },
    "宫泽谦吾": {
        "game_name": "Little Busters!",
        "birthday": "4-30",
        "aliases": "",
        "img_path": [
            "宫泽谦吾.jpg"
        ],
        "cv": null,
        "staff": null,
        "tag": "Little Busters",
        "company_name": "VISUAL ARTS / Key",
        "like": null,
        "age": "180cm/72kg",
        "presenter": null,
        "others": null
    },
    "冈崎直幸": {
        "game_name": "CLANNAD",
        "birthday": "5-1",
        "aliases": "",
        "img_path": [
            "冈崎直幸.jpg"
        ],
        "cv": "中博史",
        "staff": null,
        "tag": null,
        "company_name": "VISUAL ARTS / Key",
        "like": null,
        "age": "170cm/60kg",
        "presenter": null,
        "others": null
    },
    "天王寺瑚太朗": {
        "game_name": "Rewrite",
        "birthday": "5-2",
        "aliases": "",
        "img_path": [
            "天王寺瑚太朗.jpg"
        ],
        "cv": "森田成一",
        "staff": "樋上いたる",
        "tag": null,
        "company_name": "Key",
        "like": null,
        "age": null,
        "presenter": null,
        "others": null
    },
    "枣恭介": {
        "game_name": "Little Busters!",
        "birthday": "5-4",
        "aliases": "",
        "img_path": [
            "枣恭介.jpg"
        ],
        "cv": "緑川光",
        "staff": null,
        "tag": null,
        "company_name": "Key、VISUAL ARTS",
        "like": null,
        "age": null,
        "presenter": null,
        "others": null
    },
    "仓田佐祐理": {
        "game_name": "Kanon",
        "birthday": "5-5",
        "aliases": "",
        "img_path": [
            "仓田佐祐理.jpeg"
        ],
        "cv": "川上とも子",
        "staff": "樋上いたる",
        "tag": null,
        "company_name": "Key",
        "like": null,
        "age": null,
        "presenter": null,
        "others": null
    },
    "夏洛特": {
        "game_name": "Heaven Burns Red",
        "birthday": "5-7",
        "aliases": "",
        "img_path": [
            "夏洛特.webp"
        ],
        "cv": "会泽纱弥",
        "staff": null,
        "tag": "31X",
        "company_name": "VISUAL ARTS / Key",
        "like": null,
        "age": "150cm",
        "presenter": null,
        "others": null
    },
    "利田美咲": {
        "game_name": "LOOPERS",
        "birthday": "5-8",
        "aliases": "",
        "img_path": [],
        "cv": null,
        "staff": null,
        "tag": null,
        "company_name": "VISUAL ARTS / Key",
        "like": null,
        "age": null,
        "presenter": null,
        "others": null
    },
    "友利奈绪": {
        "game_name": "Charlotte",
        "birthday": "5-11",
        "aliases": "",
        "img_path": [
            "友利奈绪.jpeg"
        ],
        "cv": "佐仓绫音",
        "staff": "Na-Ga",
        "tag": null,
        "company_name": "Key",
        "like": null,
        "age": null,
        "presenter": null,
        "others": null
    },
    "室伏理沙": {
        "game_name": "Heaven Burns Red",
        "birthday": "5-12",
        "aliases": "",
        "img_path": [
            "室伏理沙.png"
        ],
        "cv": "中村樱",
        "staff": null,
        "tag": "31D",
        "company_name": "Key、VISUAL ARTS",
        "like": null,
        "age": "168cm",
        "presenter": null,
        "others": null
    },
    "一之濑琴美": {
        "game_name": "CLANNAD",
        "birthday": "5-13",
        "aliases": "",
        "img_path": [
            "一之濑琴美.jpeg"
        ],
        "cv": "能登麻美子",
        "staff": "樋上いたる",
        "tag": null,
        "company_name": "Key",
        "like": null,
        "age": null,
        "presenter": null,
        "others": null
    },
    "鹰原羽依里": {
        "game_name": "Summer Pockets",
        "birthday": "5-21",
        "aliases": "",
        "img_path": [
            "鹰原羽依里.png"
        ],
        "cv": "千葉翔也",
        "staff": "Na-Ga",
        "tag": "翅膀受伤白候鸟\n忘记歌唱金丝雀\n双拳皆毁拳击手\n笨口拙舌男公关",
        "company_name": "VISUAL ARTS / Key",
        "like": null,
        "age": "17y、172cm",
        "presenter": "七影、之翼",
        "others": "嗯原版终章都没露脸的工具人……但是能给乒乓球拍回血，真厉害吧。（by 七影"
    },
    "石井色叶": {
        "game_name": "Heaven Burns Red",
        "birthday": "5-26",
        "aliases": "",
        "img_path": [
            "石井色叶.webp"
        ],
        "cv": "桑原由気",
        "staff": null,
        "tag": "31D",
        "company_name": "Key、VISUAL ARTS",
        "like": null,
        "age": "156cm",
        "presenter": null,
        "others": null
    },
    "雾岛让": {
        "game_name": "LOOPERS",
        "birthday": "6-6",
        "aliases": "",
        "img_path": [
            "雾岛让.JPG"
        ],
        "cv": "江藤要介",
        "staff": "望月けい",
        "tag": null,
        "company_name": "Key",
        "like": null,
        "age": "178cm",
        "presenter": null,
        "others": null
    },
    "二阶堂三乡": {
        "game_name": "Heaven Burns Red",
        "birthday": "6-6",
        "aliases": "",
        "img_path": [
            "二阶堂三乡.jpg"
        ],
        "cv": "奈波果林",
        "staff": null,
        "tag": "31D",
        "company_name": "Key、VISUAL ARTS",
        "like": null,
        "age": "163cm",
        "presenter": null,
        "others": null
    },
    "鸣濑白羽": {
        "game_name": "Summer Pockets",
        "birthday": "6-8",
        "aliases": "",
        "img_path": [
            "鸣濑白羽.jpeg"
        ],
        "cv": "小原好美",
        "staff": "Na-Ga",
        "tag": null,
        "company_name": "VISUAL ARTS / Key",
        "like": null,
        "age": null,
        "presenter": null,
        "others": null
    },
    "春原芽衣": {
        "game_name": "CLANNAD",
        "birthday": "6-11",
        "aliases": "",
        "img_path": [
            "春原芽衣.jpeg"
        ],
        "cv": "田村ゆかり",
        "staff": "樋上いたる",
        "tag": null,
        "company_name": "Key、VISUAL ARTS",
        "like": null,
        "age": null,
        "presenter": null,
        "others": null
    },
    "能美库特莉亚芙卡": {
        "game_name": "Little Busters!",
        "birthday": "6-12",
        "aliases": "",
        "img_path": [
            "能美库特莉亚芙卡.jpeg"
        ],
        "cv": "若林直美",
        "staff": "Na-Ga",
        "tag": null,
        "company_name": "VISUAL ARTS / Key",
        "like": null,
        "age": null,
        "presenter": null,
        "others": null
    },
    "雾岛佳乃": {
        "game_name": "AIR",
        "birthday": "6-12",
        "aliases": "",
        "img_path": [
            "雾岛佳乃.jpeg"
        ],
        "cv": "岡本麻見",
        "staff": "樋上いたる",
        "tag": null,
        "company_name": "Key",
        "like": null,
        "age": "156cm、B82/W53/H80",
        "presenter": null,
        "others": null
    },
    "志麻子": {
        "game_name": "Rewrite",
        "birthday": "6-13",
        "aliases": "",
        "img_path": [
            "志麻子.jpeg"
        ],
        "cv": "渡邉佳美",
        "staff": "樋上いたる",
        "tag": null,
        "company_name": "Key",
        "like": null,
        "age": "115cm、B56/W44/H55",
        "presenter": null,
        "others": null
    },
    "中津静流": {
        "game_name": "Rewrite",
        "birthday": "6-18",
        "aliases": "",
        "img_path": [
            "中津静流.png"
        ],
        "cv": "すずきけいこ",
        "staff": "樋上いたる",
        "tag": null,
        "company_name": "Key",
        "like": null,
        "age": "149cm、B75/W52/H73",
        "presenter": null,
        "others": null
    },
    "藏里见": {
        "game_name": "Heaven Burns Red",
        "birthday": "6-18",
        "aliases": "",
        "img_path": [
            "藏里见.webp"
        ],
        "cv": "井泽美香子",
        "staff": null,
        "tag": "30G",
        "company_name": "VISUAL ARTS / Key",
        "like": null,
        "age": "172cm",
        "presenter": null,
        "others": null
    },
    "茅森月歌": {
        "game_name": "Heaven Burns Red",
        "birthday": "6-24",
        "aliases": "",
        "img_path": [
            "茅森月歌.png"
        ],
        "cv": "楠木ともり/Vo：XAI",
        "staff": null,
        "tag": "31A",
        "company_name": "Key",
        "like": null,
        "age": "159cm",
        "presenter": null,
        "others": null
    },
    "樱庭星罗": {
        "game_name": "Heaven Burns Red",
        "birthday": "6-29",
        "aliases": "",
        "img_path": [
            "樱庭星罗.webp"
        ],
        "cv": "田泽茉纯",
        "staff": null,
        "tag": "31C",
        "company_name": "Key、VISUAL ARTS",
        "like": null,
        "age": "171cm",
        "presenter": null,
        "others": null
    },
    "神山识": {
        "game_name": "Summer Pockets REFLECTION BLUE",
        "birthday": "7-4",
        "aliases": "",
        "img_path": [
            "神山识.png"
        ],
        "cv": "ファイルーズあい",
        "staff": "ふむゆん",
        "tag": null,
        "company_name": "Key",
        "like": null,
        "age": "14岁、144cm、B73/W54/H74",
        "presenter": null,
        "others": null
    },
    "苍井绘梨花": {
        "game_name": "Heaven Burns Red",
        "birthday": "7-7",
        "aliases": "",
        "img_path": [
            "苍井绘梨花.webp"
        ],
        "cv": "宫下早纪",
        "staff": null,
        "tag": "31B",
        "company_name": "Key",
        "like": null,
        "age": "158cm",
        "presenter": null,
        "others": null
    },
    "朝仓可怜": {
        "game_name": "Heaven Burns Red",
        "birthday": "7-11",
        "aliases": "",
        "img_path": [
            "朝仓可怜.png"
        ],
        "cv": "芹泽优/Vo：铃木このみ",
        "staff": null,
        "tag": "31A",
        "company_name": "Key",
        "like": "垃圾食品、FPS游戏",
        "age": "158cm",
        "presenter": null,
        "others": null
    },
    "西九条灯花": {
        "game_name": "Rewrite",
        "birthday": "7-12",
        "aliases": "",
        "img_path": [
            "西九条灯花.jpeg"
        ],
        "cv": "田中涼子",
        "staff": "樋上いたる",
        "tag": null,
        "company_name": "Key",
        "like": null,
        "age": "167cm、B88/W61/H87",
        "presenter": null,
        "others": null
    },
    "有月初": {
        "game_name": "库特wafter",
        "birthday": "7-16",
        "aliases": "",
        "img_path": [
            "有月初.JPG"
        ],
        "cv": "由宇翼",
        "staff": "Na-Ga",
        "tag": null,
        "company_name": "Key、VISUAL ARTS",
        "like": null,
        "age": "159cm、44kg、B79/W56/H80",
        "presenter": null,
        "others": null
    },
    "伊吹风子": {
        "game_name": "CLANNAD",
        "birthday": "7-20",
        "aliases": "",
        "img_path": [
            "伊吹风子.jpeg"
        ],
        "cv": "野中藍",
        "staff": "樋上いたる",
        "tag": null,
        "company_name": "Key、VISUAL ARTS",
        "like": null,
        "age": "150cm、41kg、B78/W54/H79",
        "presenter": null,
        "others": null
    },
    "古河秋生": {
        "game_name": "CLANNAD",
        "birthday": "7-20",
        "aliases": "",
        "img_path": [
            "古河秋生.JPG"
        ],
        "cv": "置鮎龍太郎",
        "staff": "樋上いたる",
        "tag": null,
        "company_name": "Key、VISUAL ARTS",
        "like": null,
        "age": "175cm、68kg",
        "presenter": null,
        "others": null
    },
    "平良明": {
        "game_name": "LOOPERS",
        "birthday": "7-21",
        "aliases": "",
        "img_path": [],
        "cv": "",
        "staff": null,
        "tag": "",
        "company_name": "Key、VISUAL ARTS",
        "like": null,
        "age": "",
        "presenter": null,
        "others": null
    },
    "天音巫呼": {
        "game_name": "Heaven Burns Red",
        "birthday": "7-22",
        "aliases": "",
        "img_path": [
            "天音巫呼.png"
        ],
        "cv": "宫崎珠子",
        "staff": null,
        "tag": "31C",
        "company_name": "Key、VISUAL ARTS",
        "like": null,
        "age": "129cm",
        "presenter": null,
        "others": null
    },
    "神尾观铃": {
        "game_name": "AIR",
        "birthday": "7-23",
        "aliases": "",
        "img_path": [
            "神尾观铃.jpeg"
        ],
        "cv": "川上とも子",
        "staff": "樋上いたる",
        "tag": null,
        "company_name": "Key",
        "like": null,
        "age": "159cm、46kg、B83/W55/H82",
        "presenter": null,
        "others": null
    },
    "神户小鸟": {
        "game_name": "Rewrite",
        "birthday": "7-26",
        "aliases": "",
        "img_path": [
            "神户小鸟.jpeg"
        ],
        "cv": "斎藤千和",
        "staff": "樋上いたる",
        "tag": null,
        "company_name": "Key",
        "like": null,
        "age": "156cm、44kg、B83/W54/H83",
        "presenter": null,
        "others": null
    },
    "卡罗尔利帕": {
        "game_name": "Heaven Burns Red",
        "birthday": "8-2",
        "aliases": "",
        "img_path": [
            "卡罗尔利帕.webp"
        ],
        "cv": "八卷アンナ",
        "staff": null,
        "tag": "31X",
        "company_name": "VISUAL ARTS / Key",
        "like": null,
        "age": "164cm",
        "presenter": null,
        "others": null
    },
    "宫泽有纪宁": {
        "game_name": "CLANNAD",
        "birthday": "8-7",
        "aliases": "",
        "img_path": [
            "宫泽有纪宁.jpeg"
        ],
        "cv": "榎本温子",
        "staff": "樋上いたる",
        "tag": null,
        "company_name": "Key、VISUAL ARTS",
        "like": null,
        "age": "157cm、45kg",
        "presenter": null,
        "others": null
    },
    "夏目祈": {
        "game_name": "Heaven Burns Red",
        "birthday": "8-15",
        "aliases": "",
        "img_path": [
            "夏目祈.webp"
        ],
        "cv": "筑山苑佳",
        "staff": null,
        "tag": "31F",
        "company_name": "VISUAL ARTS / Key",
        "like": null,
        "age": "154cm",
        "presenter": null,
        "others": null
    },
    "西园美鱼": {
        "game_name": "Little Busters!",
        "birthday": "8-22",
        "aliases": "",
        "img_path": [
            "西园美鱼.jpeg"
        ],
        "cv": "河原木志穂",
        "staff": "Na-Ga",
        "tag": null,
        "company_name": "VISUAL ARTS / Key",
        "like": null,
        "age": "153cm、41kg、B75/W55/H79",
        "presenter": null,
        "others": null
    },
    "凤千早": {
        "game_name": "Rewrite",
        "birthday": "8-24",
        "aliases": "",
        "img_path": [
            "凤千早.jpeg"
        ],
        "cv": "篠宮沙弥",
        "staff": "樋上いたる",
        "tag": null,
        "company_name": "Key",
        "like": null,
        "age": "159cm、46kg、B82/W55/H84",
        "presenter": null,
        "others": null
    },
    "山胁邦伊瓦尔": {
        "game_name": "Heaven Burns Red",
        "birthday": "8-25",
        "aliases": "",
        "img_path": [
            "山胁邦伊瓦尔.webp"
        ],
        "cv": "千本木彩花",
        "staff": null,
        "tag": "31C",
        "company_name": "Key、VISUAL ARTS",
        "like": null,
        "age": "156cm",
        "presenter": null,
        "others": null
    },
    "幸村俊夫": {
        "game_name": "CLANNAD",
        "birthday": "8-27",
        "aliases": "",
        "img_path": [
            "幸村俊夫.jpg"
        ],
        "cv": "青野武/多田野曜平",
        "staff": "樋上いたる",
        "tag": null,
        "company_name": "Key、VISUAL ARTS",
        "like": null,
        "age": "162cm、52kg",
        "presenter": null,
        "others": null
    },
    "伊座并杏子": {
        "game_name": "成神之日",
        "birthday": "8-29",
        "aliases": "",
        "img_path": [
            "伊座并杏子.jpg"
        ],
        "cv": "石川由依",
        "staff": "",
        "tag": null,
        "company_name": "Key、VISUAL ARTS",
        "like": null,
        "age": "17",
        "presenter": null,
        "others": null
    },
    "紬文德斯": {
        "game_name": "Summer Pockets",
        "birthday": "8-31",
        "aliases": "",
        "img_path": [
            "紬文德斯.jpeg"
        ],
        "cv": "岩井映美里",
        "staff": "永山ゆうのん",
        "tag": null,
        "company_name": "VISUAL ARTS / Key",
        "like": "趣味：ぬいぐるみ集め\n好物：わたあめ\n座右の銘：私は私を探しています",
        "age": "16岁、152cm、38kg、B78/W56/H80",
        "presenter": null,
        "others": null
    },
    "加藤羽未": {
        "game_name": "Summer Pockets",
        "birthday": "9-1",
        "aliases": "",
        "img_path": [
            "加藤羽未.jpeg"
        ],
        "cv": "田中あいみ",
        "staff": "Na-Ga",
        "tag": null,
        "company_name": "VISUAL ARTS / Key",
        "like": null,
        "age": "12岁、130cm、29kg、B/W/H：坡度很小/稍稍有点细/唰的一下",
        "presenter": null,
        "others": null
    },
    "枣铃": {
        "game_name": "Little Busters!",
        "birthday": "9-2",
        "aliases": "",
        "img_path": [
            "枣铃.jpeg"
        ],
        "cv": "民安ともえ",
        "staff": "Na-Ga",
        "tag": null,
        "company_name": "Key、VISUAL ARTS",
        "like": null,
        "age": "153cm、43kg、B77/W54/H80",
        "presenter": null,
        "others": null
    },
    "水濑李": {
        "game_name": "Heaven Burns Red",
        "birthday": "9-6",
        "aliases": "",
        "img_path": [
            "水濑李.webp"
        ],
        "cv": "小路裕夕",
        "staff": null,
        "tag": "31B",
        "company_name": "Key",
        "like": null,
        "age": "154cm",
        "presenter": null,
        "others": null
    },
    "藤林杏": {
        "game_name": "CLANNAD",
        "birthday": "9-9",
        "aliases": "",
        "img_path": [
            "藤林杏.jpeg"
        ],
        "cv": "広橋涼",
        "staff": "樋上いたる",
        "tag": null,
        "company_name": "Key、VISUAL ARTS",
        "like": null,
        "age": "160cm、46kg、B82/W56/H82",
        "presenter": null,
        "others": null
    },
    "藤林椋": {
        "game_name": "CLANNAD",
        "birthday": "9-9",
        "aliases": "",
        "img_path": [
            "藤林椋.jpeg"
        ],
        "cv": "神田朱未",
        "staff": "樋上いたる",
        "tag": null,
        "company_name": "Key、VISUAL ARTS",
        "like": null,
        "age": "159cm、47kg",
        "presenter": null,
        "others": null
    },
    "昼田贵理子": {
        "game_name": "LOOPERS",
        "birthday": "9-13",
        "aliases": "",
        "img_path": [
            "昼田贵理子.png"
        ],
        "cv": "河野ひより",
        "staff": "望月けい",
        "tag": null,
        "company_name": "Key",
        "like": "喜欢的事情: 与Leona聊天、自拍",
        "age": "159cm",
        "presenter": null,
        "others": null
    },
    "和泉由希": {
        "game_name": "Heaven Burns Red",
        "birthday": "9-17",
        "aliases": "",
        "img_path": [
            "和泉由希.webp"
        ],
        "cv": "前川凉子",
        "staff": null,
        "tag": "31A",
        "company_name": "Key",
        "like": "吐槽",
        "age": "160cm",
        "presenter": null,
        "others": null
    },
    "空门苍": {
        "game_name": "Summer Pockets",
        "birthday": "9-20",
        "aliases": "",
        "img_path": [
            "空门苍.jpeg"
        ],
        "cv": "高森奈津美",
        "staff": "和泉つばす",
        "tag": null,
        "company_name": "VISUAL ARTS / Key",
        "like": "趣味：昼寝\n好物：かき氷\n座右の銘：果報は寝て待つ",
        "age": "16岁、160cm、46kg、B85/W59/H86",
        "presenter": null,
        "others": null
    },
    "空门蓝": {
        "game_name": "Summer Pockets",
        "birthday": "9-20",
        "aliases": "",
        "img_path": [
            "空门蓝.jpg"
        ],
        "cv": "高森奈津美",
        "staff": "和泉つばす",
        "tag": null,
        "company_name": "VISUAL ARTS / Key",
        "like": null,
        "age": "16岁、B87/W58/H87",
        "presenter": null,
        "others": null
    },
    "水濑秋子": {
        "game_name": "Kanon",
        "birthday": "9-23",
        "aliases": "",
        "img_path": [
            "水濑秋子.jpg"
        ],
        "cv": "皆口裕子",
        "staff": "樋上いたる",
        "tag": null,
        "company_name": "Key",
        "like": null,
        "age": "165cm、50kg、B86/W57/H83",
        "presenter": null,
        "others": null
    },
    "丸山奏多": {
        "game_name": "Heaven Burns Red",
        "birthday": "10-1",
        "aliases": "",
        "img_path": [
            "丸山奏多.webp"
        ],
        "cv": "河野ひより",
        "staff": null,
        "tag": "31F",
        "company_name": "VISUAL ARTS / Key",
        "like": null,
        "age": "139cm",
        "presenter": null,
        "others": null
    },
    "古河早苗": {
        "game_name": "CLANNAD",
        "birthday": "10-5",
        "aliases": "",
        "img_path": [
            "古河早苗.jpg"
        ],
        "cv": "井上喜久子",
        "staff": "樋上いたる",
        "tag": null,
        "company_name": "Key、VISUAL ARTS",
        "like": null,
        "age": "158cm、45kg",
        "presenter": null,
        "others": null
    },
    "艾琳雷顿明": {
        "game_name": "Heaven Burns Red",
        "birthday": "10-7",
        "aliases": "",
        "img_path": [
            "艾琳雷顿明.webp"
        ],
        "cv": "Marika",
        "staff": null,
        "tag": "31X",
        "company_name": "VISUAL ARTS / Key",
        "like": null,
        "age": "143cm",
        "presenter": null,
        "others": null
    },
    "加纳天善": {
        "game_name": "Summer Pockets",
        "birthday": "10-10",
        "aliases": "",
        "img_path": [
            "加纳天善.png"
        ],
        "cv": "浜田洋平",
        "staff": "Na-Ga",
        "tag": null,
        "company_name": "VISUAL ARTS / Key",
        "like": "趣味：卓球\n好物：わかめ",
        "age": "16岁、178cm、69kg",
        "presenter": null,
        "others": null
    },
    "二木佳奈多": {
        "game_name": "Little Busters!",
        "birthday": "10-13",
        "aliases": "",
        "img_path": [
            "二木佳奈多.jpeg"
        ],
        "cv": "すずきけいこ",
        "staff": "樋上いたる",
        "tag": null,
        "company_name": "Key、VISUAL ARTS",
        "like": null,
        "age": "163 cm、47kg、B80/W57/H82",
        "presenter": null,
        "others": null
    },
    "三枝叶留佳": {
        "game_name": "Little Busters!",
        "birthday": "10-13",
        "aliases": "",
        "img_path": [
            "三枝叶留佳.jpeg"
        ],
        "cv": null,
        "staff": "樋上いたる",
        "tag": null,
        "company_name": "Key、VISUAL ARTS",
        "like": null,
        "age": "163cm、49kg、B81/W59/H82",
        "presenter": null,
        "others": null
    },
    "坂上智代": {
        "game_name": "CLANNAD、智代After",
        "birthday": "10-14",
        "aliases": "",
        "img_path": [
            "坂上智代.jpeg"
        ],
        "cv": "桑島法子、田中涼子",
        "staff": "樋上いたる",
        "tag": null,
        "company_name": "Key、VISUAL ARTS",
        "like": null,
        "age": null,
        "presenter": null,
        "others": null
    },
    "岬镜子": {
        "game_name": "Summer Pockets",
        "birthday": "10-18",
        "aliases": "",
        "img_path": [
            "岬镜子.jpeg"
        ],
        "cv": "高本めぐみ",
        "staff": "ふむゆん",
        "tag": null,
        "company_name": "VISUAL ARTS / Key",
        "like": null,
        "age": null,
        "presenter": null,
        "others": null
    },
    "朱鹭户沙耶": {
        "game_name": "Little Busters! EX",
        "birthday": "10-21",
        "aliases": "",
        "img_path": [
            "朱鹭户沙耶.jpeg"
        ],
        "cv": "櫻井浩美",
        "staff": "Na-Ga",
        "tag": null,
        "company_name": "Key、VISUAL ARTS",
        "like": null,
        "age": null,
        "presenter": null,
        "others": null
    },
    "伊达朱里": {
        "game_name": "Heaven Burns Red",
        "birthday": "10-21",
        "aliases": "",
        "img_path": [
            "伊达朱里.webp"
        ],
        "cv": "大野柚布子",
        "staff": null,
        "tag": "31D",
        "company_name": "Key、VISUAL ARTS",
        "like": null,
        "age": "154cm",
        "presenter": null,
        "others": null
    },
    "逢川惠": {
        "game_name": "Heaven Burns Red",
        "birthday": "10-28",
        "aliases": "",
        "img_path": [
            "逢川惠.jpg"
        ],
        "cv": "伊波杏树",
        "staff": null,
        "tag": "31A",
        "company_name": "Key",
        "like": null,
        "age": "159cm",
        "presenter": null,
        "others": null
    },
    "冈崎朋也": {
        "game_name": "CLANNAD",
        "birthday": "10-30",
        "aliases": "",
        "img_path": [
            "冈崎朋也.jpg"
        ],
        "cv": "中村悠一",
        "staff": "樋上いたる",
        "tag": null,
        "company_name": "Key、VISUAL ARTS",
        "like": null,
        "age": null,
        "presenter": null,
        "others": null
    },
    "国见玉": {
        "game_name": "Heaven Burns Red",
        "birthday": "11-1",
        "aliases": "",
        "img_path": [
            "国见玉.webp",
            "国见玉.png"
        ],
        "cv": "古贺葵",
        "staff": null,
        "tag": "31A",
        "company_name": "Key、VISUAL ARTS",
        "like": null,
        "age": "137cm",
        "presenter": null,
        "others": null
    },
    "瑞原蓝娜": {
        "game_name": "Heaven Burns Red",
        "birthday": "11-2",
        "aliases": "",
        "img_path": [
            "瑞原蓝娜.webp"
        ],
        "cv": "星谷美绪",
        "staff": null,
        "tag": "31D",
        "company_name": "Key、VISUAL ARTS",
        "like": null,
        "age": "141cm",
        "presenter": null,
        "others": null
    },
    "神尾晴子": {
        "game_name": "AIR",
        "birthday": "11-3",
        "aliases": "",
        "img_path": [
            "神尾晴子.jpg"
        ],
        "cv": "久川绫",
        "staff": null,
        "tag": "",
        "company_name": "Key、VISUAL ARTS",
        "like": "喝酒",
        "age": "168cm/49kg B:88/W:57/H:85 28岁",
        "presenter": null,
        "others": null
    },
    "冰室忧希": {
        "game_name": "库特wafter",
        "birthday": "11-3",
        "aliases": "",
        "img_path": [],
        "cv": null,
        "staff": null,
        "tag": null,
        "company_name": "Key、VISUAL ARTS",
        "like": null,
        "age": null,
        "presenter": null,
        "others": null
    },
    "井之原真人": {
        "game_name": "Little Busters!",
        "birthday": "11-6",
        "aliases": "",
        "img_path": [
            "井之原真人.png"
        ],
        "cv": "神奈延年",
        "staff": null,
        "tag": "Little Busters",
        "company_name": "Key、VISUAL ARTS",
        "like": null,
        "age": "183cm/80kg",
        "presenter": null,
        "others": null
    },
    "吉野晴彦": {
        "game_name": "Rewrite",
        "birthday": "11-7",
        "aliases": "",
        "img_path": [
            "吉野晴彦.png"
        ],
        "cv": "柳田淳一",
        "staff": "樋上いたる",
        "tag": null,
        "company_name": "Key",
        "like": null,
        "age": null,
        "presenter": null,
        "others": null
    },
    "樋口圣华": {
        "game_name": "Heaven Burns Red",
        "birthday": "11-8",
        "aliases": "",
        "img_path": [
            "樋口圣华.webp"
        ],
        "cv": "山根绮",
        "staff": null,
        "tag": "31B",
        "company_name": "Key、VISUAL ARTS",
        "like": null,
        "age": "151cm",
        "presenter": null,
        "others": null
    },
    "黑泽真希": {
        "game_name": "Heaven Burns Red",
        "birthday": "11-22",
        "aliases": "",
        "img_path": [
            "黑泽真希.webp"
        ],
        "cv": "黑濑ゆうこ",
        "staff": null,
        "tag": "31F",
        "company_name": "VISUAL ARTS / Key",
        "like": null,
        "age": "163cm",
        "presenter": null,
        "others": null
    },
    "大岛一千子": {
        "game_name": "Heaven Burns Red",
        "birthday": "11-29",
        "aliases": "",
        "img_path": [
            "大岛一千子.webp"
        ],
        "cv": "日向葵",
        "staff": null,
        "tag": "31E",
        "company_name": "Key、VISUAL ARTS",
        "like": null,
        "age": "160cm",
        "presenter": null,
        "others": null
    },
    "大岛二以奈": {
        "game_name": "Heaven Burns Red",
        "birthday": "11-29",
        "aliases": "",
        "img_path": [
            "大岛二以奈.png"
        ],
        "cv": "金子彩花",
        "staff": null,
        "tag": "31E",
        "company_name": "Key、VISUAL ARTS",
        "like": null,
        "age": "163cm",
        "presenter": null,
        "others": null
    },
    "大岛三野里": {
        "game_name": "Heaven Burns Red",
        "birthday": "11-29",
        "aliases": "",
        "img_path": [
            "大岛三野里.webp"
        ],
        "cv": "中岛由贵",
        "staff": null,
        "tag": "31E",
        "company_name": "Key、VISUAL ARTS",
        "like": null,
        "age": "158cm",
        "presenter": null,
        "others": null
    },
    "大岛四叶草": {
        "game_name": "Heaven Burns Red",
        "birthday": "11-29",
        "aliases": "",
        "img_path": [
            "大岛四叶草.jpg"
        ],
        "cv": "内山茉莉",
        "staff": null,
        "tag": "31E",
        "company_name": "Key、VISUAL ARTS",
        "like": null,
        "age": "139cm",
        "presenter": null,
        "others": null
    },
    "大岛五十铃": {
        "game_name": "Heaven Burns Red",
        "birthday": "11-29",
        "aliases": "",
        "img_path": [
            "大岛五十铃.png"
        ],
        "cv": "中野さいま",
        "staff": null,
        "tag": "31E",
        "company_name": "Key、VISUAL ARTS",
        "like": null,
        "age": "154cm",
        "presenter": null,
        "others": null
    },
    "大岛六宇亚": {
        "game_name": "Heaven Burns Red",
        "birthday": "11-29",
        "aliases": "",
        "img_path": [
            "大岛六宇亚.webp"
        ],
        "cv": "福嶋美里衣",
        "staff": null,
        "tag": "31E",
        "company_name": "Key、VISUAL ARTS",
        "like": null,
        "age": "157cm",
        "presenter": null,
        "others": null
    },
    "月城最中": {
        "game_name": "Heaven Burns Red",
        "birthday": "12-1",
        "aliases": "",
        "img_path": [
            "月城最中.webp"
        ],
        "cv": "松本沙罗",
        "staff": null,
        "tag": "30G",
        "company_name": "VISUAL ARTS / Key",
        "like": null,
        "age": "170cm",
        "presenter": null,
        "others": null
    },
    "鸣濑小鸠": {
        "game_name": "Summer Pockets",
        "birthday": "12-2",
        "aliases": "",
        "img_path": [
            "鸣濑小鸠.png"
        ],
        "cv": "白石稔",
        "staff": null,
        "tag": null,
        "company_name": "Key、VISUAL ARTS",
        "like": null,
        "age": "185cm/96kg",
        "presenter": null,
        "others": null
    },
    "笹濑川佐佐美": {
        "game_name": "Little Busters! EX",
        "birthday": "12-3",
        "aliases": "",
        "img_path": [
            "笹濑川佐佐美.jpeg"
        ],
        "cv": "民安ともえ",
        "staff": null,
        "tag": null,
        "company_name": "Key、VISUAL ARTS",
        "like": null,
        "age": null,
        "presenter": null,
        "others": null
    },
    "芳野祐介": {
        "game_name": "CLANNAD",
        "birthday": "12-5",
        "aliases": "",
        "img_path": [
            "芳野祐介.jpg"
        ],
        "cv": "绿川光",
        "staff": null,
        "tag": null,
        "company_name": "Key、VISUAL ARTS",
        "like": null,
        "age": "179cm/63kg",
        "presenter": null,
        "others": null
    },
    "天野美汐": {
        "game_name": "Kanon",
        "birthday": "12-6",
        "aliases": "",
        "img_path": [
            "天野美汐.jpg"
        ],
        "cv": "坂本真绫",
        "staff": null,
        "tag": null,
        "company_name": "Key、VISUAL ARTS",
        "like": null,
        "age": "159cm/44kg 80/53/79 16岁",
        "presenter": null,
        "others": null
    },
    "李映夏": {
        "game_name": "Heaven Burns Red",
        "birthday": "12-14",
        "aliases": "",
        "img_path": [
            "李映夏.png"
        ],
        "cv": "东乡しえり",
        "staff": null,
        "tag": "31X",
        "company_name": "VISUAL ARTS / Key",
        "like": null,
        "age": "158cm",
        "presenter": null,
        "others": null
    },
    "远野美凪": {
        "game_name": "AIR",
        "birthday": "12-22",
        "aliases": "",
        "img_path": [
            "远野美凪.jpeg"
        ],
        "cv": "柚木涼香",
        "staff": "樋上いたる",
        "tag": null,
        "company_name": "Key",
        "like": null,
        "age": null,
        "presenter": null,
        "others": null
    },
    "水濑名雪": {
        "game_name": "Kanon",
        "birthday": "12-23",
        "aliases": "",
        "img_path": [
            "水濑名雪.jpeg"
        ],
        "cv": "國府田マリ子",
        "staff": "樋上いたる",
        "tag": null,
        "company_name": "Key",
        "like": null,
        "age": null,
        "presenter": null,
        "others": null
    },
    "此花露西娅": {
        "game_name": "Rewrite",
        "birthday": "12-23",
        "aliases": "",
        "img_path": [
            "此花露西娅.gif"
        ],
        "cv": "朝樹りさ",
        "staff": "樋上いたる",
        "tag": null,
        "company_name": "Key",
        "like": null,
        "age": null,
        "presenter": null,
        "others": null
    },
    "古河渚": {
        "game_name": "CLANNAD",
        "birthday": "12-24",
        "aliases": "",
        "img_path": [
            "古河渚.jpeg"
        ],
        "cv": "中原麻衣",
        "staff": "樋上いたる",
        "tag": null,
        "company_name": "Key、VISUAL ARTS",
        "like": null,
        "age": null,
        "presenter": null,
        "others": null
    },
    "菅原千惠": {
        "game_name": "Heaven Burns Red",
        "birthday": "12-25",
        "aliases": "",
        "img_path": [
            "菅原千惠.png"
        ],
        "cv": "根本京里",
        "staff": null,
        "tag": "30G",
        "company_name": "VISUAL ARTS / Key",
        "like": null,
        "age": "152cm",
        "presenter": null,
        "others": null
    },
    "西森柚咲": {
        "game_name": "Charlotte",
        "birthday": "12-27",
        "aliases": "",
        "img_path": [
            "西森柚咲.png"
        ],
        "cv": "内田真礼",
        "staff": "Na-Ga",
        "tag": null,
        "company_name": "Key",
        "like": null,
        "age": null,
        "presenter": null,
        "others": null
    },
    "ホリー": {
        "game_name": "LOOPERS",
        "birthday": "12-27",
        "aliases": "",
        "img_path": [],
        "cv": null,
        "staff": null,
        "tag": null,
        "company_name": "Key",
        "like": null,
        "age": null,
        "presenter": null,
        "others": null
    },
    "小满": {
        "game_name": "AIR",
        "birthday": "unknown",
        "aliases": "",
        "img_path": [
            "小满.jpeg"
        ],
        "cv": "田村由香里",
        "staff": "樋上いたる",
        "tag": null,
        "company_name": "Key、VISUAL ARTS",
        "like": null,
        "age": null,
        "presenter": null,
        "others": null
    },
    "神奈备命": {
        "game_name": "AIR",
        "birthday": "unknown",
        "aliases": "",
        "img_path": [
            "神奈备命.jpg"
        ],
        "cv": "西村千奈美",
        "staff": "樋上いたる",
        "tag": null,
        "company_name": "Key",
        "like": null,
        "age": null,
        "presenter": null,
        "others": null
    },
    "冈崎汐": {
        "game_name": "CLANNAD",
        "birthday": "unknown",
        "aliases": "",
        "img_path": [
            "冈崎汐.jpeg"
        ],
        "cv": "兴梠里美",
        "staff": "樋上いたる",
        "tag": null,
        "company_name": "Key",
        "like": null,
        "age": null,
        "presenter": null,
        "others": null
    },
    "篝": {
        "game_name": "Rewrite",
        "birthday": "unknown",
        "aliases": "",
        "img_path": [
            "篝.jpeg"
        ],
        "cv": "朝樹りさ",
        "staff": "樋上いたる",
        "tag": null,
        "company_name": "Key",
        "like": null,
        "age": null,
        "presenter": null,
        "others": null
    },
    "亚斯茗": {
        "game_name": "Rewrite",
        "birthday": "unknown",
        "aliases": "",
        "img_path": [
            "亚斯茗.jpeg"
        ],
        "cv": "朝樹りさ",
        "staff": "樋上いたる",
        "tag": null,
        "company_name": "Key",
        "like": null,
        "age": null,
        "presenter": null,
        "others": null
    },
    "仲村由理": {
        "game_name": "Angel Beats!",
        "birthday": "unknown",
        "aliases": "",
        "img_path": [
            "仲村由理.jpeg"
        ],
        "cv": "樱井浩美",
        "staff": null,
        "tag": null,
        "company_name": "Key",
        "like": null,
        "age": null,
        "presenter": null,
        "others": null
    },
    "立华奏": {
        "game_name": "Angel Beats!",
        "birthday": "unknown",
        "aliases": "",
        "img_path": [
            "立华奏.png"
        ],
        "cv": "花泽香菜",
        "staff": null,
        "tag": null,
        "company_name": "Key",
        "like": null,
        "age": null,
        "presenter": null,
        "others": null
    },
    "由依": {
        "game_name": "Angel Beats!",
        "birthday": "unknown",
        "aliases": "",
        "img_path": [
            "由依.jpeg"
        ],
        "cv": null,
        "staff": null,
        "tag": null,
        "company_name": "Key",
        "like": null,
        "age": null,
        "presenter": null,
        "others": null
    },
    "岩泽雅美": {
        "game_name": "Angel Beats!",
        "birthday": "unknown",
        "aliases": "",
        "img_path": [
            "岩泽雅美.jpeg"
        ],
        "cv": null,
        "staff": null,
        "tag": null,
        "company_name": "Key",
        "like": null,
        "age": null,
        "presenter": null,
        "others": null
    },
    "入江美雪": {
        "game_name": "Angel Beats!",
        "birthday": "unknown",
        "aliases": "",
        "img_path": [
            "入江美雪.jpeg"
        ],
        "cv": null,
        "staff": null,
        "tag": null,
        "company_name": "Key",
        "like": null,
        "age": null,
        "presenter": null,
        "others": null
    },
    "关根诗织": {
        "game_name": "Angel Beats!",
        "birthday": "unknown",
        "aliases": "",
        "img_path": [
            "关根诗织.jpeg"
        ],
        "cv": null,
        "staff": null,
        "tag": null,
        "company_name": "Key",
        "like": null,
        "age": null,
        "presenter": null,
        "others": null
    },
    "乙坂步未": {
        "game_name": "Charlotte",
        "birthday": "unknown",
        "aliases": "",
        "img_path": [
            "乙坂步未.jpeg"
        ],
        "cv": "麻仓桃",
        "staff": "Na-Ga",
        "tag": null,
        "company_name": "Key",
        "like": null,
        "age": null,
        "presenter": null,
        "others": null
    },
    "星野梦美": {
        "game_name": "星之梦",
        "birthday": "unknown",
        "aliases": "",
        "img_path": [
            "星野梦美.jpeg"
        ],
        "cv": "麻仓桃",
        "staff": null,
        "tag": null,
        "company_name": "Key",
        "like": null,
        "age": null,
        "presenter": null,
        "others": null
    },
    "诗音那": {
        "game_name": "Harmonia",
        "birthday": "unknown",
        "aliases": "",
        "img_path": [
            "诗音那.jpeg"
        ],
        "cv": null,
        "staff": null,
        "tag": null,
        "company_name": "Key",
        "like": null,
        "age": null,
        "presenter": null,
        "others": null
    },
    "提比": {
        "game_name": "Harmonia",
        "birthday": "unknown",
        "aliases": "",
        "img_path": [
            "提比.jpeg"
        ],
        "cv": null,
        "staff": null,
        "tag": null,
        "company_name": "Key",
        "like": null,
        "age": null,
        "presenter": null,
        "others": null
    },
    "菲莉娅": {
        "game_name": "星之终途",
        "birthday": "unknown",
        "aliases": "",
        "img_path": [
            "菲莉娅.png"
        ],
        "cv": null,
        "staff": null,
        "tag": null,
        "company_name": "Key",
        "like": null,
        "age": null,
        "presenter": null,
        "others": null
    },
    "佐藤雏": {
        "game_name": "成神之日",
        "birthday": "unknown",
        "aliases": "",
        "img_path": [
            "佐藤雏.png"
        ],
        "cv": null,
        "staff": null,
        "tag": null,
        "company_name": "Key",
        "like": null,
        "age": null,
        "presenter": null,
        "others": null
    },
    "灰樱": {
        "game_name": "天籁人偶",
        "birthday": "unknown",
        "aliases": "",
        "img_path": [
            "灰樱.png"
        ],
        "cv": null,
        "staff": null,
        "tag": null,
        "company_name": "Key",
        "like": null,
        "age": null,
        "presenter": null,
        "others": null
    },
    "土豆": {
        "game_name": "AIR",
        "birthday": "unknown",
        "aliases": "",
        "img_path": [
            "土豆.jpeg"
        ],
        "cv": null,
        "staff": null,
        "tag": null,
        "company_name": "Key",
        "like": null,
        "age": null,
        "presenter": null,
        "others": null
    },
    "乌鸦": {
        "game_name": "AIR",
        "birthday": "unknown",
        "aliases": "",
        "img_path": [
            "乌鸦.jpeg"
        ],
        "cv": null,
        "staff": null,
        "tag": null,
        "company_name": "Key",
        "like": null,
        "age": null,
        "presenter": null,
        "others": null
    },
    "鲷鱼烧": {
        "game_name": "Kanon",
        "birthday": "unknown",
        "aliases": "",
        "img_path": [
            "鲷鱼烧.jpeg"
        ],
        "cv": null,
        "staff": null,
        "tag": null,
        "company_name": "Key",
        "like": null,
        "age": null,
        "presenter": null,
        "others": null
    },
    "海星": {
        "game_name": "CLANNAD",
        "birthday": "unknown",
        "aliases": "",
        "img_path": [
            "海星.jpeg"
        ],
        "cv": null,
        "staff": null,
        "tag": null,
        "company_name": "Key",
        "like": null,
        "age": null,
        "presenter": null,
        "others": null
    },
    "牡丹": {
        "game_name": "CLANNAD",
        "birthday": "unknown",
        "aliases": "",
        "img_path": [
            "牡丹.png"
        ],
        "cv": null,
        "staff": null,
        "tag": null,
        "company_name": "Key",
        "like": null,
        "age": null,
        "presenter": null,
        "others": null
    },
    "麻枝准": {
        "game_name": "Key",
        "birthday": "unknown",
        "aliases": "",
        "img_path": [
            "麻枝准.png"
        ],
        "cv": "麻枝准",
        "staff": "麻枝准",
        "tag": null,
        "company_name": "Key",
        "like": null,
        "age": null,
        "presenter": null,
        "others": null
    }
}